ercotutils/__init__.py
ercotutils/misutil.py
ercotutils-1.1.0.dist-info/LICENSE.txt
ercotutils-1.1.0.dist-info/METADATA
ercotutils-1.1.0.dist-info/WHEEL
ercotutils-1.1.0.dist-info/top_level.txt
ercotutils-1.1.0.dist-info/RECORD
