Metadata-Version: 2.1
Name: ercotutils
Version: 1.1.0
Summary: ERCOT utils for Python
Home-page: https://github.com/mmccollom/ercot_mis_pylib
Author: Matthew McCollom
Author-email: matthewmccollom1989@gmail.com
Project-URL: Bug Tracker, https://github.com/mmccollom/ercot_mis_pylib/issues
Classifier: Programming Language :: Python :: 3
Classifier: License :: OSI Approved :: MIT License
Classifier: Operating System :: OS Independent
Requires-Python: >=3.7
License-File: LICENSE.txt
Requires-Dist: requests (>=2.5.0)
